stacker/__init__.py
stacker/awscli_yamlhelper.py
stacker/context.py
stacker/environment.py
stacker/exceptions.py
stacker/plan.py
stacker/session_cache.py
stacker/stack.py
stacker/status.py
stacker/target.py
stacker/tokenize_userdata.py
stacker/ui.py
stacker/util.py
stacker/variables.py
stacker/actions/__init__.py
stacker/actions/base.py
stacker/actions/build.py
stacker/actions/destroy.py
stacker/actions/diff.py
stacker/actions/graph.py
stacker/actions/info.py
stacker/blueprints/__init__.py
stacker/blueprints/base.py
stacker/blueprints/raw.py
stacker/blueprints/testutil.py
stacker/blueprints/variables/__init__.py
stacker/blueprints/variables/types.py
stacker/commands/__init__.py
stacker/commands/stacker/__init__.py
stacker/commands/stacker/base.py
stacker/commands/stacker/build.py
stacker/commands/stacker/destroy.py
stacker/commands/stacker/diff.py
stacker/commands/stacker/graph.py
stacker/commands/stacker/info.py
stacker/config/__init__.py
stacker/config/translators/__init__.py
stacker/config/translators/kms.py
stacker/dag/__init__.py
stacker/hooks/__init__.py
stacker/hooks/aws_lambda.py
stacker/hooks/command.py
stacker/hooks/ecs.py
stacker/hooks/iam.py
stacker/hooks/keypair.py
stacker/hooks/route53.py
stacker/hooks/utils.py
stacker/logger/__init__.py
stacker/lookups/__init__.py
stacker/lookups/registry.py
stacker/lookups/handlers/__init__.py
stacker/lookups/handlers/ami.py
stacker/lookups/handlers/default.py
stacker/lookups/handlers/dynamodb.py
stacker/lookups/handlers/envvar.py
stacker/lookups/handlers/file.py
stacker/lookups/handlers/hook_data.py
stacker/lookups/handlers/kms.py
stacker/lookups/handlers/output.py
stacker/lookups/handlers/rxref.py
stacker/lookups/handlers/split.py
stacker/lookups/handlers/ssmstore.py
stacker/lookups/handlers/xref.py
stacker/providers/__init__.py
stacker/providers/base.py
stacker/providers/aws/__init__.py
stacker/providers/aws/default.py
stacker/tests/__init__.py
stacker/tests/conftest.py
stacker/tests/factories.py
stacker-1.7.2.dist-info/AUTHORS.rst
stacker-1.7.2.dist-info/LICENSE
stacker-1.7.2.dist-info/METADATA
stacker-1.7.2.dist-info/WHEEL
stacker-1.7.2.dist-info/top_level.txt
stacker-1.7.2.dist-info/RECORD
