Metadata-Version: 2.1
Name: stacker
Version: 1.7.2
Summary: AWS CloudFormation Stack manager
Home-page: https://github.com/cloudtools/stacker
Author: Michael Barrett
Author-email: loki77@gmail.com
License: New BSD license
Platform: UNKNOWN
Classifier: Development Status :: 5 - Production/Stable
Classifier: Environment :: Console
Classifier: License :: OSI Approved :: BSD License
Classifier: Programming Language :: Python :: 2.7
Classifier: Programming Language :: Python :: 3.5
Classifier: Programming Language :: Python :: 3.6
Requires-Dist: future
Requires-Dist: troposphere (>=1.9.0)
Requires-Dist: botocore (>=1.12.111)
Requires-Dist: boto3 (<2.0,>=1.9.111)
Requires-Dist: PyYAML (>=3.13b1)
Requires-Dist: awacs (>=0.6.0)
Requires-Dist: gitpython (<3.0,>=2.0)
Requires-Dist: jinja2 (<3.0a,>=2.7)
Requires-Dist: schematics (<2.1.0,>=2.0.1)
Requires-Dist: formic2
Requires-Dist: python-dateutil (<3.0,>=2.0)
Requires-Dist: MarkupSafe (<2.0)
Requires-Dist: more-itertools (<6.0.0)
Requires-Dist: rsa (==4.5)
Requires-Dist: python-jose (<3.2.0)
Provides-Extra: testing
Requires-Dist: pytest (~=4.3) ; extra == 'testing'
Requires-Dist: pytest-cov (~=2.6) ; extra == 'testing'
Requires-Dist: mock (~=2.0) ; extra == 'testing'
Requires-Dist: moto[awslambda] (~=1.3.16) ; extra == 'testing'
Requires-Dist: testfixtures (~=4.10.0) ; extra == 'testing'
Requires-Dist: flake8-future-import ; extra == 'testing'
